EiscatDIRAC/__init__.py
EiscatDIRAC/DataManagementSystem/__init__.py
EiscatDIRAC/DataManagementSystem/DB/__init__.py
EiscatDIRAC/DataManagementSystem/DB/FileCatalogComponents/__init__.py
EiscatDIRAC/DataManagementSystem/DB/FileCatalogComponents/SecurityPolicies/EiscatPolicy.py
EiscatDIRAC/DataManagementSystem/DB/FileCatalogComponents/SecurityPolicies/__init__.py
EiscatDIRAC/WebApp/__init__.py
EiscatDIRAC/WebApp/web.cfg
EiscatDIRAC/WebApp/handler/JobLaunchpadHandler.py
EiscatDIRAC/WebApp/handler/__init__.py
EiscatDIRAC/WebApp/static/EiscatDIRAC/FileCatalog/classes/FileCatalog.js
EiscatDIRAC/WebApp/static/EiscatDIRAC/JobLaunchpad/classes/JobLaunchpad.js
EiscatDIRAC/WebApp/template/root.tpl
EiscatDIRAC-0.3.0a3.dist-info/METADATA
EiscatDIRAC-0.3.0a3.dist-info/WHEEL
EiscatDIRAC-0.3.0a3.dist-info/entry_points.txt
EiscatDIRAC-0.3.0a3.dist-info/top_level.txt
EiscatDIRAC-0.3.0a3.dist-info/RECORD
